{"semester_id": "2019A", "schedule_end": "2019-04-23T02:47:30.561762", "horizon_days": 7.0, "total_priority_value": 24336.260622155496, "schedule_start": "2019-04-16T02:47:30.561762", "resources": {"4m0a.doma.sor": {"priority_value": 24336.260622155496, "reservations": [{"priority": 1923.7216540738532, "start": "2019-04-16T08:55:00", "resource": "4m0a.doma.sor", "end": "2019-04-16T09:53:01", "request_id": 103}, {"priority": 723.9937879000053, "start": "2019-04-16T08:30:00", "resource": "4m0a.doma.sor", "end": "2019-04-16T08:52:01", "request_id": 102}, {"priority": 494.95133787130135, "start": "2019-04-17T01:20:00", "resource": "4m0a.doma.sor", "end": "2019-04-17T01:43:33", "request_id": 101}, {"priority": 492.7976573011175, "start": "2019-04-16T23:14:35", "resource": "4m0a.doma.sor", "end": "2019-04-16T23:38:08", "request_id": 100}, {"priority": 368.1961111952049, "start": "2019-04-17T06:20:00", "resource": "4m0a.doma.sor", "end": "2019-04-17T06:37:33", "request_id": 99}, {"priority": 493.839817331545, "start": "2019-04-17T06:40:00", "resource": "4m0a.doma.sor", "end": "2019-04-17T07:03:33", "request_id": 98}, {"priority": 597.7185980699834, "start": "2019-04-17T08:05:00", "resource": "4m0a.doma.sor", "end": "2019-04-17T08:33:33", "request_id": 97}, {"priority": 493.9100241607216, "start": "2019-04-17T07:05:00", "resource": "4m0a.doma.sor", "end": "2019-04-17T07:28:33", "request_id": 96}, {"priority": 495.83662859098104, "start": "2019-04-17T04:35:00", "resource": "4m0a.doma.sor", "end": "2019-04-17T04:58:33", "request_id": 95}, {"priority": 494.78145708301537, "start": "2019-04-17T04:10:00", "resource": "4m0a.doma.sor", "end": "2019-04-17T04:33:33", "request_id": 94}, {"priority": 602.0222046110414, "start": "2019-04-17T07:30:00", "resource": "4m0a.doma.sor", "end": "2019-04-17T07:58:33", "request_id": 93}, {"priority": 494.1595261399546, "start": "2019-04-17T03:45:00", "resource": "4m0a.doma.sor", "end": "2019-04-17T04:08:33", "request_id": 92}, {"priority": 367.0150648807116, "start": "2019-04-17T03:25:00", "resource": "4m0a.doma.sor", "end": "2019-04-17T03:42:33", "request_id": 91}, {"priority": 367.45787743397034, "start": "2019-04-17T01:00:00", "resource": "4m0a.doma.sor", "end": "2019-04-17T01:17:33", "request_id": 90}, {"priority": 492.4782838818974, "start": "2019-04-17T03:00:00", "resource": "4m0a.doma.sor", "end": "2019-04-17T03:23:33", "request_id": 89}, {"priority": 305.23677726361683, "start": "2019-04-17T00:25:00", "resource": "4m0a.doma.sor", "end": "2019-04-17T00:39:33", "request_id": 88}, {"priority": 304.46821489347667, "start": "2019-04-17T00:10:00", "resource": "4m0a.doma.sor", "end": "2019-04-17T00:24:33", "request_id": 87}, {"priority": 306.44075749733025, "start": "2019-04-16T23:40:00", "resource": "4m0a.doma.sor", "end": "2019-04-16T23:54:33", "request_id": 86}, {"priority": 304.632093292265, "start": "2019-04-16T23:55:00", "resource": "4m0a.doma.sor", "end": "2019-04-17T00:09:33", "request_id": 85}, {"priority": 369.40330798109, "start": "2019-04-17T00:40:00", "resource": "4m0a.doma.sor", "end": "2019-04-17T00:57:33", "request_id": 84}, {"priority": 494.53099033774794, "start": "2019-04-17T02:35:00", "resource": "4m0a.doma.sor", "end": "2019-04-17T02:58:33", "request_id": 83}, {"priority": 492.79296549304985, "start": "2019-04-17T02:10:00", "resource": "4m0a.doma.sor", "end": "2019-04-17T02:33:33", "request_id": 82}, {"priority": 494.57937831630073, "start": "2019-04-17T01:45:00", "resource": "4m0a.doma.sor", "end": "2019-04-17T02:08:33", "request_id": 81}, {"priority": 495.5151106140055, "start": "2019-04-16T04:26:17", "resource": "4m0a.doma.sor", "end": "2019-04-16T04:41:20", "request_id": 80}, {"priority": 494.8885620477449, "start": "2019-04-16T05:50:00", "resource": "4m0a.doma.sor", "end": "2019-04-16T06:05:03", "request_id": 79}, {"priority": 763.0420780133487, "start": "2019-04-16T07:15:00", "resource": "4m0a.doma.sor", "end": "2019-04-16T07:38:03", "request_id": 78}, {"priority": 762.9252210551864, "start": "2019-04-16T03:35:00", "resource": "4m0a.doma.sor", "end": "2019-04-16T03:58:03", "request_id": 77}, {"priority": 1254.0246444639258, "start": "2019-04-16T06:35:00", "resource": "4m0a.doma.sor", "end": "2019-04-16T07:13:03", "request_id": 76}, {"priority": 568.295517721465, "start": "2019-04-16T08:10:00", "resource": "4m0a.doma.sor", "end": "2019-04-16T08:28:03", "request_id": 75}, {"priority": 570.6203260072498, "start": "2019-04-16T07:50:03", "resource": "4m0a.doma.sor", "end": "2019-04-16T08:08:06", "request_id": 74}, {"priority": 758.9751663997329, "start": "2019-04-16T06:10:00", "resource": "4m0a.doma.sor", "end": "2019-04-16T06:33:03", "request_id": 73}, {"priority": 566.1496106025425, "start": "2019-04-16T03:15:00", "resource": "4m0a.doma.sor", "end": "2019-04-16T03:33:03", "request_id": 72}, {"priority": 729.0502319942557, "start": "2019-04-16T04:00:00", "resource": "4m0a.doma.sor", "end": "2019-04-16T04:23:03", "request_id": 70}, {"priority": 357.3347405369833, "start": "2019-04-16T03:01:44", "resource": "4m0a.doma.sor", "end": "2019-04-16T03:14:47", "request_id": 66}, {"priority": 342.4808271470494, "start": "2019-04-16T09:55:00", "resource": "4m0a.doma.sor", "end": "2019-04-16T10:08:03", "request_id": 64}, {"priority": 1404.9163289456262, "start": "2019-04-17T08:35:00", "resource": "4m0a.doma.sor", "end": "2019-04-17T09:28:33", "request_id": 63}, {"priority": 1411.7037239425968, "start": "2019-04-17T05:25:00", "resource": "4m0a.doma.sor", "end": "2019-04-17T06:18:33", "request_id": 62}, {"priority": 633.8400572348147, "start": "2019-04-16T05:25:00", "resource": "4m0a.doma.sor", "end": "2019-04-16T05:48:03", "request_id": 61}, {"priority": 621.1538853380856, "start": "2019-04-17T05:00:23", "resource": "4m0a.doma.sor", "end": "2019-04-17T05:23:26", "request_id": 60}, {"priority": 626.3800744907005, "start": "2019-04-16T04:59:20", "resource": "4m0a.doma.sor", "end": "2019-04-16T05:22:23", "request_id": 59}], "dark_intervals": [{"start": "2019-04-16T02:47:30.561762", "end": "2019-04-16T10:10:29.282490"}, {"start": "2019-04-16T23:14:35.424135", "end": "2019-04-17T10:11:02.961180"}, {"start": "2019-04-17T23:13:34.052600", "end": "2019-04-18T10:11:36.577275"}, {"start": "2019-04-18T23:12:33.502262", "end": "2019-04-19T10:12:10.143722"}, {"start": "2019-04-19T23:11:33.797779", "end": "2019-04-20T10:12:43.672804"}, {"start": "2019-04-20T23:10:34.962858", "end": "2019-04-21T10:13:17.175622"}, {"start": "2019-04-21T23:09:37.020422", "end": "2019-04-22T10:13:50.661795"}, {"start": "2019-04-22T23:08:39.992818", "end": "2019-04-23T02:47:30.561762"}]}}}